lensed_umap/__init__.py
lensed_umap/api.py
lensed_umap/fast_impl.py
lensed_umap/tests/__init__.py
lensed_umap/tests/test_lenses.py
lensed_umap-0.1.2.dist-info/LICENSE
lensed_umap-0.1.2.dist-info/METADATA
lensed_umap-0.1.2.dist-info/WHEEL
lensed_umap-0.1.2.dist-info/top_level.txt
lensed_umap-0.1.2.dist-info/RECORD
