Metadata-Version: 2.1
Name: lensed_umap
Version: 0.1.2
Summary: Untangle UMAP with lenses.
Home-page: https://github.com/vda-lab/lensed_umap
Author: Jelmer Bot
Author-email: jelmer.bot@uhasselt.be
License: BSD-3-Clause license
Project-URL: Code, https://github.com/vda-lab/lensed_umap
Project-URL: Issue tracker, https://github.com/vda-lab/lensed_umap/issues
Classifier: Development Status :: 4 - Beta
Classifier: License :: OSI Approved :: BSD License
Classifier: Intended Audience :: Science/Research
Classifier: Topic :: Scientific/Engineering
Classifier: Natural Language :: English
Classifier: Operating System :: OS Independent
Classifier: Programming Language :: Python :: 3 :: Only
Requires-Python: >=3.9
License-File: LICENSE
Requires-Dist: numpy >=1.23
Requires-Dist: pandas >=2.1.1
Requires-Dist: scipy >=1.9
Requires-Dist: scikit-learn >=1.1
Requires-Dist: umap-learn >=0.5.4
Requires-Dist: numba >=0.57.1
